Metadata-Version: 2.1
Name: XX-distributions
Version: 0.1
Summary: Gaussian and Binomial distributions
Author: Xi Xi
License-File: license.txt
